<annotation>
	<folder>dataset</folder>
	<filename>acrylic-illustration-colorful-flowers-butterfly-260nw-44051800.jpg</filename>
	<path>C:\Users\ssafy\shutterscrape\dataset\acrylic-illustration-colorful-flowers-butterfly-260nw-44051800.jpg</path>
	<source>
		<database>Unknown</database>
	</source>
	<size>
		<width>262</width>
		<height>280</height>
		<depth>3</depth>
	</size>
	<segmented>0</segmented>
	<object>
		<name>flower</name>
		<pose>Unspecified</pose>
		<truncated>0</truncated>
		<difficult>0</difficult>
		<bndbox>
			<xmin>30</xmin>
			<ymin>13</ymin>
			<xmax>100</xmax>
			<ymax>94</ymax>
		</bndbox>
	</object>
	<object>
		<name>flower</name>
		<pose>Unspecified</pose>
		<truncated>0</truncated>
		<difficult>0</difficult>
		<bndbox>
			<xmin>10</xmin>
			<ymin>92</ymin>
			<xmax>64</xmax>
			<ymax>170</ymax>
		</bndbox>
	</object>
	<object>
		<name>flower</name>
		<pose>Unspecified</pose>
		<truncated>0</truncated>
		<difficult>0</difficult>
		<bndbox>
			<xmin>2</xmin>
			<ymin>171</ymin>
			<xmax>47</xmax>
			<ymax>211</ymax>
		</bndbox>
	</object>
	<object>
		<name>flower</name>
		<pose>Unspecified</pose>
		<truncated>0</truncated>
		<difficult>0</difficult>
		<bndbox>
			<xmin>58</xmin>
			<ymin>87</ymin>
			<xmax>142</xmax>
			<ymax>160</ymax>
		</bndbox>
	</object>
	<object>
		<name>flower</name>
		<pose>Unspecified</pose>
		<truncated>0</truncated>
		<difficult>0</difficult>
		<bndbox>
			<xmin>132</xmin>
			<ymin>49</ymin>
			<xmax>241</xmax>
			<ymax>175</ymax>
		</bndbox>
	</object>
	<object>
		<name>flower</name>
		<pose>Unspecified</pose>
		<truncated>0</truncated>
		<difficult>0</difficult>
		<bndbox>
			<xmin>143</xmin>
			<ymin>176</ymin>
			<xmax>194</xmax>
			<ymax>232</ymax>
		</bndbox>
	</object>
	<object>
		<name>flower</name>
		<pose>Unspecified</pose>
		<truncated>0</truncated>
		<difficult>0</difficult>
		<bndbox>
			<xmin>181</xmin>
			<ymin>159</ymin>
			<xmax>232</xmax>
			<ymax>196</ymax>
		</bndbox>
	</object>
</annotation>
