<annotation>
	<folder>sky</folder>
	<filename>cute-outline-illustration-cloud-that-260nw-2151593061.jpg</filename>
	<path>C:\Users\ssafy\shutterscrape\sky\cute-outline-illustration-cloud-that-260nw-2151593061.jpg</path>
	<source>
		<database>Unknown</database>
	</source>
	<size>
		<width>259</width>
		<height>280</height>
		<depth>1</depth>
	</size>
	<segmented>0</segmented>
	<object>
		<name>cloud</name>
		<pose>Unspecified</pose>
		<truncated>0</truncated>
		<difficult>0</difficult>
		<bndbox>
			<xmin>135</xmin>
			<ymin>95</ymin>
			<xmax>237</xmax>
			<ymax>164</ymax>
		</bndbox>
	</object>
	<object>
		<name>sun</name>
		<pose>Unspecified</pose>
		<truncated>0</truncated>
		<difficult>0</difficult>
		<bndbox>
			<xmin>30</xmin>
			<ymin>127</ymin>
			<xmax>139</xmax>
			<ymax>234</ymax>
		</bndbox>
	</object>
</annotation>
