<annotation>
	<folder>person1</folder>
	<filename>vector-illustration-childs-picture-done-260nw-28925710.jpg</filename>
	<path>C:\Users\multicampus\Downloads\특화프로젝트\person1\person1\vector-illustration-childs-picture-done-260nw-28925710.jpg</path>
	<source>
		<database>Unknown</database>
	</source>
	<size>
		<width>347</width>
		<height>280</height>
		<depth>3</depth>
	</size>
	<segmented>0</segmented>
	<object>
		<name>tree</name>
		<pose>Unspecified</pose>
		<truncated>0</truncated>
		<difficult>0</difficult>
		<bndbox>
			<xmin>235</xmin>
			<ymin>54</ymin>
			<xmax>316</xmax>
			<ymax>232</ymax>
		</bndbox>
	</object>
	<object>
		<name>tree</name>
		<pose>Unspecified</pose>
		<truncated>0</truncated>
		<difficult>0</difficult>
		<bndbox>
			<xmin>37</xmin>
			<ymin>58</ymin>
			<xmax>119</xmax>
			<ymax>229</ymax>
		</bndbox>
	</object>
	<object>
		<name>building</name>
		<pose>Unspecified</pose>
		<truncated>0</truncated>
		<difficult>0</difficult>
		<bndbox>
			<xmin>106</xmin>
			<ymin>57</ymin>
			<xmax>232</xmax>
			<ymax>232</ymax>
		</bndbox>
	</object>
	<object>
		<name>sun</name>
		<pose>Unspecified</pose>
		<truncated>0</truncated>
		<difficult>0</difficult>
		<bndbox>
			<xmin>39</xmin>
			<ymin>24</ymin>
			<xmax>219</xmax>
			<ymax>99</ymax>
		</bndbox>
	</object>
</annotation>
