<annotation>
	<folder>person1</folder>
	<filename>vector-background-childrens-drawings-houses-260nw-276208160.jpg</filename>
	<path>C:\Users\multicampus\Downloads\특화프로젝트\person1\person1\vector-background-childrens-drawings-houses-260nw-276208160.jpg</path>
	<source>
		<database>Unknown</database>
	</source>
	<size>
		<width>260</width>
		<height>280</height>
		<depth>3</depth>
	</size>
	<segmented>0</segmented>
	<object>
		<name>sun</name>
		<pose>Unspecified</pose>
		<truncated>0</truncated>
		<difficult>0</difficult>
		<bndbox>
			<xmin>51</xmin>
			<ymin>29</ymin>
			<xmax>130</xmax>
			<ymax>108</ymax>
		</bndbox>
	</object>
	<object>
		<name>building</name>
		<pose>Unspecified</pose>
		<truncated>0</truncated>
		<difficult>0</difficult>
		<bndbox>
			<xmin>120</xmin>
			<ymin>143</ymin>
			<xmax>189</xmax>
			<ymax>218</ymax>
		</bndbox>
	</object>
	<object>
		<name>tree</name>
		<pose>Unspecified</pose>
		<truncated>0</truncated>
		<difficult>0</difficult>
		<bndbox>
			<xmin>182</xmin>
			<ymin>148</ymin>
			<xmax>242</xmax>
			<ymax>212</ymax>
		</bndbox>
	</object>
</annotation>
